ndx_fret/__init__.py
ndx_fret/nwbn_gui_forms.py
ndx_fret/test.py
ndx_fret/spec/ndx-fret.extensions.yaml
ndx_fret/spec/ndx-fret.namespace.yaml
ndx_fret-0.2.1.dist-info/LICENSE.txt
ndx_fret-0.2.1.dist-info/METADATA
ndx_fret-0.2.1.dist-info/WHEEL
ndx_fret-0.2.1.dist-info/top_level.txt
ndx_fret-0.2.1.dist-info/RECORD
